MyTopsis/__init__.py
MyTopsis/topsis.py
Topsis-UCS633/__init__.py
Topsis-UCS633/topsis.py
Topsis_UCS633/__init__.py
Topsis_UCS633/topsis.py
topsis-101703177/__init__.py
topsis-101703177/topsis.py
topsis_101703177-0.0.1.dist-info/DESCRIPTION.rst
topsis_101703177-0.0.1.dist-info/METADATA
topsis_101703177-0.0.1.dist-info/RECORD
topsis_101703177-0.0.1.dist-info/WHEEL
topsis_101703177-0.0.1.dist-info/metadata.json
topsis_101703177-0.0.1.dist-info/top_level.txt
